deva/__init__.py
deva/__main__.py
deva/_version.py
deva/py.typed
deva/cli/__init__.py
deva/cli/application.py
deva/cli/base.py
deva/cli/terminal.py
deva/cli/config/__init__.py
deva/cli/config/explore/__init__.py
deva/cli/config/find/__init__.py
deva/cli/config/restore/__init__.py
deva/cli/config/set/__init__.py
deva/cli/config/show/__init__.py
deva/cli/env/__init__.py
deva/cli/env/dev/__init__.py
deva/cli/env/dev/utils.py
deva/cli/env/dev/code/__init__.py
deva/cli/env/dev/gui/__init__.py
deva/cli/env/dev/ls/__init__.py
deva/cli/env/dev/remove/__init__.py
deva/cli/env/dev/run/__init__.py
deva/cli/env/dev/shell/__init__.py
deva/cli/env/dev/start/__init__.py
deva/cli/env/dev/status/__init__.py
deva/cli/env/dev/stop/__init__.py
deva/cli/inv/__init__.py
deva/cli/self/__init__.py
deva/cli/self/dep/__init__.py
deva/cli/self/dep/lock/Dockerfile
deva/cli/self/dep/lock/__init__.py
deva/cli/self/dep/sync/__init__.py
deva/cli/self/remove/__init__.py
deva/cli/self/restore/__init__.py
deva/cli/self/update/__init__.py
deva/config/__init__.py
deva/config/constants.py
deva/config/file.py
deva/config/utils.py
deva/config/model/__init__.py
deva/config/model/env.py
deva/config/model/git.py
deva/config/model/github.py
deva/config/model/orgs.py
deva/config/model/storage.py
deva/config/model/terminal.py
deva/env/__init__.py
deva/env/models.py
deva/env/ssh.py
deva/env/dev/__init__.py
deva/env/dev/interface.py
deva/env/dev/types/__init__.py
deva/env/dev/types/linux_container.py
deva/env/shells/__init__.py
deva/env/shells/bash.py
deva/env/shells/interface.py
deva/env/shells/nu.py
deva/env/shells/zsh.py
deva/tools/__init__.py
deva/tools/base.py
deva/tools/docker.py
deva/tools/uv.py
deva/utils/__init__.py
deva/utils/ci.py
deva/utils/fs.py
deva/utils/platform.py
deva/utils/process.py
deva/utils/retry.py
deva/utils/ssh.py
deva/utils/venv.py
datadog_agent_dev-0.4.3.data/data/deva-data/pyproject.toml
datadog_agent_dev-0.4.3.data/data/deva-data/uv.lock
datadog_agent_dev-0.4.3.dist-info/METADATA
datadog_agent_dev-0.4.3.dist-info/WHEEL
datadog_agent_dev-0.4.3.dist-info/entry_points.txt
datadog_agent_dev-0.4.3.dist-info/licenses/LICENSE.txt
datadog_agent_dev-0.4.3.dist-info/RECORD
